setup.py
frasco_aws/__init__.py
frasco_aws/upload.py
frasco_aws.egg-info/PKG-INFO
frasco_aws.egg-info/SOURCES.txt
frasco_aws.egg-info/dependency_links.txt
frasco_aws.egg-info/not-zip-safe
frasco_aws.egg-info/requires.txt
frasco_aws.egg-info/top_level.txt