Metadata-Version: 1.0
Name: frasco-aws
Version: 0.1.5
Summary: Amazon Web Services integration for Frasco
Home-page: http://github.com/frascoweb/frasco-aws
Author: Maxime Bouroumeau-Fuseau
Author-email: maxime.bouroumeau@gmail.com
License: MIT
Platform: any
